tkdesigner/__init__.py
tkdesigner/cli.py
tkdesigner/conftest.py
tkdesigner/constants.py
tkdesigner/designer.py
tkdesigner/figma/README.md
tkdesigner/figma/__init__.py
tkdesigner/figma/custom_elements.py
tkdesigner/figma/endpoints.py
tkdesigner/figma/frame.py
tkdesigner/figma/node.py
tkdesigner/figma/vector_elements.py
tkdesigner/template.py
tkdesigner/utils.py
tkdesigner-1.0.5.dist-info/entry_points.txt
tkdesigner-1.0.5.dist-info/LICENSE
tkdesigner-1.0.5.dist-info/WHEEL
tkdesigner-1.0.5.dist-info/METADATA
tkdesigner-1.0.5.dist-info/RECORD
