Metadata-Version: 2.1
Name: tkdesigner
Version: 1.0.5
Summary: CLI Package for Tkinter-Designer
Home-page: https://github.com/ParthJadhav/Tkinter-Designer
License: BSD-3-Clause
Keywords: tkinter,drag-and-drop,figma,gui,easy
Author: ParthJadhav
Author-email: jadhavparth99@gmail.com
Requires-Python: >=3.8,<4.0
Classifier: License :: OSI Approved :: BSD License
Classifier: Operating System :: OS Independent
Classifier: Programming Language :: Python :: 3
Classifier: Programming Language :: Python :: 3.8
Classifier: Programming Language :: Python :: 3.9
Classifier: Programming Language :: Python :: 3.10
Classifier: Programming Language :: Python :: 3.11
Classifier: Programming Language :: Python :: 3
Requires-Dist: Jinja2 (==3.0.1)
Requires-Dist: Pillow (>=8.4.0,<9.0.0)
Requires-Dist: requests (==2.25.1)
Requires-Dist: urllib3 (>=1.26.6,<2.0.0)
Project-URL: Bug Tracker, https://github.com/ParthJadhav/Tkinter-Designer/issues
Project-URL: Documentation, https://github.com/ParthJadhav/Tkinter-Designer
Project-URL: Repository, https://github.com/ParthJadhav/Tkinter-Designer
